{
  "project_info": {
    "project_number": "368512616958",
    "project_id": "soulmateapp-fddb3",
    "storage_bucket": "soulmateapp-fddb3.appspot.com"
  },
  "client": [
    {
      "client_info": {
        "mobilesdk_app_id": "1:368512616958:android:b4ab0bd0f83a0fabe7d8af",
        "android_client_info": {
          "package_name": "com.example.soulmate"
        }
      },
      "oauth_client": [
        {
          "client_id": "368512616958-6phntqmg1eaqgevseu2gfeq6v76tfnv5.apps.googleusercontent.com",
          "client_type": 3
        }
      ],
      "api_key": [
        {
          "current_key": "AIzaSyAUPep-TLqyYoDb6ln3T2aDtgjbhm2UdhI"
        }
      ],
      "services": {
        "appinvite_service": {
          "other_platform_oauth_client": [
            {
              "client_id": "368512616958-6phntqmg1eaqgevseu2gfeq6v76tfnv5.apps.googleusercontent.com",
              "client_type": 3
            }
          ]
        }
      }
    }
  ],
  "configuration_version": "1"
}